oneNeuron/__init__.py
oneNeuron/perceptron.py
oneNeuron/testing.py
oneNeuron/utils/__init__.py
oneNeuron/utils/all_utils.py
twoNeuron/__init__.py
twoNeuron/all_utils.py
oneNeuron_pypi_TengHoo3-0.1.1.dist-info/LICENSE
oneNeuron_pypi_TengHoo3-0.1.1.dist-info/METADATA
oneNeuron_pypi_TengHoo3-0.1.1.dist-info/WHEEL
oneNeuron_pypi_TengHoo3-0.1.1.dist-info/top_level.txt
oneNeuron_pypi_TengHoo3-0.1.1.dist-info/RECORD
