Metadata-Version: 2.1
Name: oneNeuron-pypi-TengHoo3
Version: 0.1.1
Summary: Perceptron module implementation
Home-page: https://github.com/TengHoo3/oneNeuron_pypi
Author: TengHoo3
Author-email: tenghoo3@gmail.com
License: UNKNOWN
Project-URL: Bug Tracker, https://github.com/TengHoo3/oneNeuron_pypi/issues
Platform: UNKNOWN
Classifier: Programming Language :: Python :: 3
Classifier: License :: OSI Approved :: MIT License
Classifier: Operating System :: OS Independent
Requires-Python: >=3.7
License-File: LICENSE
Requires-Dist: numpy
Requires-Dist: tqdm
